parser.py
mineparser-0.0.1.dist-info/licenses/LICENSE.txt
mineparser-0.0.1.dist-info/METADATA
mineparser-0.0.1.dist-info/WHEEL
mineparser-0.0.1.dist-info/top_level.txt
mineparser-0.0.1.dist-info/RECORD
